CongPythonDaoDjangoRumenjiaocheng/README.md
CongPythonDaoDjangoRumenjiaocheng/__init__.py
CongPythonDaoDjangoRumenjiaocheng/__main__.py
CongPythonDaoDjangoRumenjiaocheng/file.epub
CongPythonDaoDjangoRumenjiaocheng/index.html
CongPythonDaoDjangoRumenjiaocheng/css/__init__.py
CongPythonDaoDjangoRumenjiaocheng/css/annotations.css
CongPythonDaoDjangoRumenjiaocheng/css/main.css
CongPythonDaoDjangoRumenjiaocheng/css/normalize.css
CongPythonDaoDjangoRumenjiaocheng/css/popup.css
CongPythonDaoDjangoRumenjiaocheng/font/__init__.py
CongPythonDaoDjangoRumenjiaocheng/font/fontello.eot
CongPythonDaoDjangoRumenjiaocheng/font/fontello.svg
CongPythonDaoDjangoRumenjiaocheng/font/fontello.ttf
CongPythonDaoDjangoRumenjiaocheng/font/fontello.woff
CongPythonDaoDjangoRumenjiaocheng/img/__init__.py
CongPythonDaoDjangoRumenjiaocheng/img/annotator-glyph-sprite.png
CongPythonDaoDjangoRumenjiaocheng/img/annotator-icon-sprite.png
CongPythonDaoDjangoRumenjiaocheng/img/apple-touch-icon.png
CongPythonDaoDjangoRumenjiaocheng/img/cancelfullscreen.png
CongPythonDaoDjangoRumenjiaocheng/img/close.png
CongPythonDaoDjangoRumenjiaocheng/img/fullscreen.png
CongPythonDaoDjangoRumenjiaocheng/img/loader.gif
CongPythonDaoDjangoRumenjiaocheng/img/menu-icon.png
CongPythonDaoDjangoRumenjiaocheng/img/save.png
CongPythonDaoDjangoRumenjiaocheng/img/saved.png
CongPythonDaoDjangoRumenjiaocheng/img/settings-s.png
CongPythonDaoDjangoRumenjiaocheng/img/settings.png
CongPythonDaoDjangoRumenjiaocheng/img/star.png
CongPythonDaoDjangoRumenjiaocheng/js/__init__.py
CongPythonDaoDjangoRumenjiaocheng/js/epub.js
CongPythonDaoDjangoRumenjiaocheng/js/epub.min.js
CongPythonDaoDjangoRumenjiaocheng/js/epub.min.map
CongPythonDaoDjangoRumenjiaocheng/js/hooks.min.js
CongPythonDaoDjangoRumenjiaocheng/js/hooks.min.map
CongPythonDaoDjangoRumenjiaocheng/js/reader.js
CongPythonDaoDjangoRumenjiaocheng/js/reader.js.map
CongPythonDaoDjangoRumenjiaocheng/js/reader.min.js
CongPythonDaoDjangoRumenjiaocheng/js/reader.min.map
cong_python_dao_django_rumenjiaocheng-2024.3.3.0.dist-info/METADATA
cong_python_dao_django_rumenjiaocheng-2024.3.3.0.dist-info/WHEEL
cong_python_dao_django_rumenjiaocheng-2024.3.3.0.dist-info/entry_points.txt
cong_python_dao_django_rumenjiaocheng-2024.3.3.0.dist-info/top_level.txt
cong_python_dao_django_rumenjiaocheng-2024.3.3.0.dist-info/RECORD
